{
  "AAB-2502": {
    "title": "Whitcomb Hotel",
    "date": "n.d.",
    "years": [
      1850,
      1999
    ],
    "folder": "S.F. Hotels-Whitcomb-(Exteriors).",
    "library_url": "http://sflib1.sfpl.org:82/record=b1007514~S0",
    "width": 502,
    "height": 400
  },
  "AAB-2503": {
    "title": "Whitcomb Hotel",
    "date": "n.d.",
    "years": [
      1850,
      1999
    ],
    "folder": "S.F. Hotels-Whitcomb-(Exteriors).",
    "library_url": "http://sflib1.sfpl.org:82/record=b1007515~S0",
    "width": 507,
    "height": 400
  },
  "AAB-2518": {
    "title": "Whitcomb Hotel",
    "date": "n.d.",
    "years": [
      1850,
      1999
    ],
    "folder": "S.F. Hotels-Whitcomb-(Exteriors).",
    "library_url": "http://sflib1.sfpl.org:82/record=b1007530~S0",
    "width": 506,
    "height": 400
  },
  "AAB-2521": {
    "title": "Whitcomb Hotel",
    "date": "n.d.",
    "years": [
      1850,
      1999
    ],
    "folder": "S.F. Hotels-Whitcomb-(Exteriors).",
    "library_url": "http://sflib1.sfpl.org:82/record=b1007533~S0",
    "width": 629,
    "height": 400
  },
  "AAB-2523": {
    "title": "Whitcomb Hotel refurbished both inside and out",
    "date": "n.d.",
    "years": [
      1850,
      1999
    ],
    "folder": "S.F. Hotels-Whitcomb-(Exteriors).",
    "library_url": "http://sflib1.sfpl.org:82/record=b1007535~S0",
    "width": 496,
    "height": 400
  },
  "AAB-2520": {
    "title": "Exterior of Whitcomb Hotel lit up with white lights",
    "date": "1912 Feb. 9",
    "years": [
      1912,
      1912
    ],
    "folder": "S.F. Hotels-Whitcomb-(Exteriors).",
    "library_url": "http://sflib1.sfpl.org:82/record=b1007532~S0",
    "width": 507,
    "height": 400
  },
  "AAB-2504": {
    "title": "Young girl standing next to a cake in the shape of the Whitcomb Hotel",
    "date": "1927 Oct. 29",
    "years": [
      1927,
      1927
    ],
    "folder": "S.F. Hotels-Whitcomb-(Exteriors).",
    "library_url": "http://sflib1.sfpl.org:82/record=b1007516~S0",
    "width": 523,
    "height": 400
  },
  "AAB-2505": {
    "title": "Whitcomb Hotel",
    "date": "1928 Mar. 14",
    "years": [
      1928,
      1928
    ],
    "folder": "S.F. Hotels-Whitcomb-(Exteriors).",
    "library_url": "http://sflib1.sfpl.org:82/record=b1007517~S0",
    "width": 536,
    "height": 400
  },
  "AAB-2524": {
    "title": "Street car crossing outside the Whitcomb Hotel",
    "date": "1942 July 15",
    "years": [
      1942,
      1942
    ],
    "folder": "S.F. Hotels-Whitcomb-(Exteriors).",
    "library_url": "http://sflib1.sfpl.org:82/record=b1007536~S0",
    "width": 489,
    "height": 400
  },
  "AAB-2514": {
    "title": "Scene of where Virginia Hepburn jumped from the Whitcomb Hotel",
    "date": "1946 Apr. 9",
    "years": [
      1946,
      1946
    ],
    "folder": "S.F. Hotels-Whitcomb-(Exteriors).",
    "library_url": "http://sflib1.sfpl.org:82/record=b1007526~S0",
    "width": 315,
    "height": 400
  },
  "AAB-2517": {
    "title": "Whitcomb Hotel",
    "date": "1951",
    "years": [
      1951,
      1951
    ],
    "folder": "S.F. Hotels-Whitcomb-(Exteriors).",
    "library_url": "http://sflib1.sfpl.org:82/record=b1007529~S0",
    "width": 554,
    "height": 400
  },
  "AAB-2516": {
    "title": "Herbert Salzbrunn with fellow Austrians visiting the Hotel Whitcomb",
    "date": "1956 June 26",
    "years": [
      1956,
      1956
    ],
    "folder": "S.F. Hotels-Whitcomb-(Exteriors).",
    "library_url": "http://sflib1.sfpl.org:82/record=b1007528~S0",
    "width": 267,
    "height": 400
  },
  "AAB-2510": {
    "title": "Whitcomb Hotel",
    "date": "1963 Jan. 18",
    "years": [
      1963,
      1963
    ],
    "folder": "S.F. Hotels-Whitcomb-(Exteriors).",
    "library_url": "http://sflib1.sfpl.org:82/record=b1007522~S0",
    "width": 499,
    "height": 400
  },
  "AAB-2513": {
    "title": "Whitcomb Hotel, 1231 Market street",
    "date": "1964 Aug. 10",
    "years": [
      1964,
      1964
    ],
    "folder": "S.F. Hotels-Whitcomb-(Exteriors).",
    "library_url": "http://sflib1.sfpl.org:82/record=b1007525~S0",
    "width": 476,
    "height": 400
  }
}