{
  "AAC-8599": {
    "title": "United Railroad streetcar number 1718 on number 12 Ocean Avenue line",
    "date": "n.d.",
    "years": [
      1850,
      1999
    ],
    "folder": "S.F. Transportation-Streetcars-Lines-United Railroads.",
    "library_url": "http://sflib1.sfpl.org:82/record=b1023455~S0",
    "width": 564,
    "height": 400
  },
  "AAC-8600": {
    "title": "United Railroad streetcar number 1552 on number 12 Ocean Avenue line",
    "date": "n.d.",
    "years": [
      1850,
      1999
    ],
    "folder": "S.F. Transportation-Streetcars-Lines-United Railroads.",
    "library_url": "http://sflib1.sfpl.org:82/record=b1023456~S0",
    "width": 561,
    "height": 400
  }
}