{
  "AAA-9792": {
    "title": "Entrance to Francis Scott Key School",
    "date": "1936 Apr. 9",
    "years": [
      1936,
      1936
    ],
    "folder": "S.F. Schools-Elementary-Francis Scott Key.",
    "library_url": "http://sflib1.sfpl.org:82/record=b1004853~S0",
    "width": 204,
    "height": 400
  },
  "AAA-9790": {
    "title": "Physical Education class at Francis Scott Key Elementary School",
    "date": "1940 Sept. 18",
    "years": [
      1940,
      1940
    ],
    "folder": "S.F. Schools-Elementary-Francis Scott Key.",
    "library_url": "http://sflib1.sfpl.org:82/record=b1004851~S0",
    "width": 751,
    "height": 400
  },
  "AAA-9794": {
    "title": "Francis Scott Key School",
    "date": "1949 Jan. 11",
    "years": [
      1949,
      1949
    ],
    "folder": "S.F. Schools-Elementary-Francis Scott Key.",
    "library_url": "http://sflib1.sfpl.org:82/record=b1004855~S0",
    "width": 334,
    "height": 400
  },
  "AAA-9791": {
    "title": "Francis Scott Key School at 1531 42nd Avenue",
    "date": "1964 June 11",
    "years": [
      1964,
      1964
    ],
    "folder": "S.F. Schools-Elementary-Francis Scott Key.",
    "library_url": "http://sflib1.sfpl.org:82/record=b1004852~S0",
    "width": 498,
    "height": 400
  },
  "AAA-9793": {
    "title": "Francis Scott Key Nursery",
    "date": "1964 June 11",
    "years": [
      1964,
      1964
    ],
    "folder": "S.F. Schools-Elementary-Francis Scott Key.",
    "library_url": "http://sflib1.sfpl.org:82/record=b1004854~S0",
    "width": 502,
    "height": 400
  }
}