{
  "AAB-0422": {
    "title": "Polytechnic High School",
    "date": "n.d.",
    "years": [
      1850,
      1999
    ],
    "folder": "S.F. Schools-Secondary-Polytechnic.",
    "library_url": "http://sflib1.sfpl.org:82/record=b1005476~S0",
    "width": 509,
    "height": 400
  },
  "AAB-0423": {
    "title": "Science class at Polytechnic High School",
    "date": "n.d.",
    "years": [
      1850,
      1999
    ],
    "folder": "S.F. Schools-Secondary-Polytechnic.",
    "library_url": "http://sflib1.sfpl.org:82/record=b1005477~S0",
    "width": 494,
    "height": 400
  },
  "AAB-0417": {
    "title": "Teachers of Polytechnic High School, 1894 - 1895",
    "date": "1894 or 1895",
    "years": [
      1894,
      1895
    ],
    "folder": "S.F. Schools-Secondary-Polytechnic.",
    "library_url": "http://sflib1.sfpl.org:82/record=b1005471~S0",
    "width": 336,
    "height": 400
  },
  "AAB-0420": {
    "title": "David Levy, wearing a mask, entertaining Martha Kruase at Polytechnic High School",
    "date": "1935 June 3",
    "years": [
      1935,
      1935
    ],
    "folder": "S.F. Schools-Secondary-Polytechnic.",
    "library_url": "http://sflib1.sfpl.org:82/record=b1005474~S0",
    "width": 716,
    "height": 400
  },
  "AAB-0421": {
    "title": "Platoon drill at Polytechnic High School",
    "date": "1935 June 18",
    "years": [
      1935,
      1935
    ],
    "folder": "S.F. Schools-Secondary-Polytechnic.",
    "library_url": "http://sflib1.sfpl.org:82/record=b1005475~S0",
    "width": 528,
    "height": 400
  },
  "AAB-0424": {
    "title": "Mr. and Mrs. Harry Marshall presenting Cadet Lieutenant Colonel Ralph E. Schultz a memorial trophy in honor of the Polytechnic High School R. O. T. C.",
    "date": "1938 Nov. 11",
    "years": [
      1938,
      1938
    ],
    "folder": "S.F. Schools-Secondary-Polytechnic.",
    "library_url": "http://sflib1.sfpl.org:82/record=b1005478~S0",
    "width": 290,
    "height": 400
  },
  "AAB-0425": {
    "title": "High school students at a dance sponsored by Polytechnic High School",
    "date": "1941 Sept. 29",
    "years": [
      1941,
      1941
    ],
    "folder": "S.F. Schools-Secondary-Polytechnic.",
    "library_url": "http://sflib1.sfpl.org:82/record=b1005479~S0",
    "width": 536,
    "height": 400
  },
  "AAB-0419": {
    "title": "Science class at Polytechnic High School",
    "date": "1957 Nov. 12",
    "years": [
      1957,
      1957
    ],
    "folder": "S.F. Schools-Secondary-Polytechnic.",
    "library_url": "http://sflib1.sfpl.org:82/record=b1005473~S0",
    "width": 646,
    "height": 400
  },
  "AAB-0418": {
    "title": "Teacher Stewart Dimon watching students Jose Medrano and Diane Fabian conduct a chemistry experiment at Polytechnic High School",
    "date": "1958 Mar. 26",
    "years": [
      1958,
      1958
    ],
    "folder": "S.F. Schools-Secondary-Polytechnic.",
    "library_url": "http://sflib1.sfpl.org:82/record=b1005472~S0",
    "width": 415,
    "height": 400
  },
  "AAB-0416": {
    "title": "Students outside the entrance to Polytechnic High School",
    "date": "1958 Oct. 16",
    "years": [
      1958,
      1958
    ],
    "folder": "S.F. Schools-Secondary-Polytechnic.",
    "library_url": "http://sflib1.sfpl.org:82/record=b1005470~S0",
    "width": 319,
    "height": 400
  },
  "AAB-0415": {
    "title": "Polytechnic High School, 701 Frederick Street",
    "date": "1964 Aug. 19",
    "years": [
      1964,
      1964
    ],
    "folder": "S.F. Schools-Secondary-Polytechnic.",
    "library_url": "http://sflib1.sfpl.org:82/record=b1005469~S0",
    "width": 482,
    "height": 400
  }
}