{
  "AAB-4269": {
    "title": "Closeup of 1937 Oldsmobile parked on Kearny Street near Jackson",
    "date": "1937",
    "years": [
      1937,
      1937
    ],
    "folder": "S.F. Streets-Kearny-1930's.",
    "library_url": "http://sflib1.sfpl.org:82/record=b1009247~S0",
    "width": 582,
    "height": 400
  },
  "AAB-4188": {
    "title": "Jackson Street from Kearny",
    "date": "1969 May",
    "years": [
      1969,
      1969
    ],
    "folder": "S.F. Streets-Jackson.",
    "library_url": "http://sflib1.sfpl.org:82/record=b1009166~S0",
    "width": 311,
    "height": 400
  }
}