{
  "AAB-4224": {
    "title": "Celebration on Kearny north from Sutter street",
    "date": "n.d.",
    "years": [
      1850,
      1999
    ],
    "folder": "S.F. Streets-Kearny-N.D.",
    "library_url": "http://sflib1.sfpl.org:82/record=b1009202~S0",
    "width": 666,
    "height": 400
  },
  "AAC-6714": {
    "title": "Doane & Henshelwood dry goods store at Sutter and Kearny streets",
    "date": "n.d.",
    "years": [
      1850,
      1999
    ],
    "folder": "S.F. Businesses-Doane & Henshelwood.",
    "library_url": "http://sflib1.sfpl.org:82/record=b1021574~S0",
    "width": 525,
    "height": 400
  },
  "AAB-5336": {
    "title": "Sutter Street west of Kearny Street",
    "date": "1869",
    "years": [
      1869,
      1869
    ],
    "folder": "S.F. Streets-Sutter-1860's.",
    "library_url": "http://sflib1.sfpl.org:82/record=b1010289~S0",
    "width": 422,
    "height": 400
  },
  "AAC-3287": {
    "title": "View of ruins along Kearny Street looking south from Sutter, showing the Chronicle, Call and Mutual Savings Bank buildings",
    "date": "1906",
    "years": [
      1906,
      1906
    ],
    "folder": "S.F. Earthquakes-1906-Streets-Kearny Street.",
    "library_url": "http://sflib1.sfpl.org:82/record=b1018162~S0",
    "width": 215,
    "height": 400
  },
  "AAB-2466": {
    "title": "Sutter Hotel at Kearny and Sutter streets",
    "date": "1957 July 9",
    "years": [
      1957,
      1957
    ],
    "folder": "S.F. Hotels-Sutter.",
    "library_url": "http://sflib1.sfpl.org:82/record=b1007478~S0",
    "width": 455,
    "height": 400
  },
  "AAB-4297": {
    "title": "Corner of Kearny and Sutter streets",
    "date": "1963 Nov. 14",
    "years": [
      1963,
      1963
    ],
    "folder": "S.F. Streets-Kearny-1960's.",
    "library_url": "http://sflib1.sfpl.org:82/record=b1009275~S0",
    "width": 322,
    "height": 400
  }
}