{
  "AAC-0638": {
    "title": "View From Russian Hill at Green and Leavenworth streets",
    "date": "1866",
    "years": [
      1866,
      1866
    ],
    "folder": "S.F. Districts-Russian Hill-1866.",
    "library_url": "http://sflib1.sfpl.org:82/record=b1015965~S0",
    "width": 555,
    "height": 400
  },
  "AAB-6291": {
    "title": "Two photos of Market Street and a drawing of an apartment building at Green and Leavenworth streets",
    "date": "1930 Nov. 10",
    "years": [
      1930,
      1930
    ],
    "folder": "S.F. Streets-Market-1930.",
    "library_url": "http://sflib1.sfpl.org:82/record=b1011232~S0",
    "width": 333,
    "height": 400
  }
}