{
  "AAC-6702": {
    "title": "Col. Andrews Diamond Palace, 221 Montgomery Street",
    "date": "n.d.",
    "years": [
      1850,
      1999
    ],
    "folder": "S.F. Businesses-Col. Andrews Diamond Palace.",
    "library_url": "http://sflib1.sfpl.org:82/record=b1021562~S0",
    "width": 320,
    "height": 400
  },
  "AAB-7336": {
    "title": "Russ House, West Side of Montgomery Street between Bush and Pine Street",
    "date": "1865",
    "years": [
      1865,
      1865
    ],
    "folder": "S.F. Streets-Montgomery-1865.",
    "library_url": "http://sflib1.sfpl.org:82/record=b1012263~S0",
    "width": 510,
    "height": 400
  }
}