{
  "AAB-2257": {
    "title": "Grand Hotel",
    "date": "n.d.",
    "years": [
      1850,
      1999
    ],
    "folder": "S.F. Hotels-Grand.",
    "library_url": "http://sflib1.sfpl.org:82/record=b1007269~S0",
    "width": 693,
    "height": 400
  },
  "AAB-2258": {
    "title": "Group of people standing on New Montgomery Street at the site of the Grand Hotel",
    "date": "n.d.",
    "years": [
      1850,
      1999
    ],
    "folder": "S.F. Hotels-Grand.",
    "library_url": "http://sflib1.sfpl.org:82/record=b1007270~S0",
    "width": 468,
    "height": 400
  },
  "AAB-2259": {
    "title": "Grand Hotel",
    "date": "n.d.",
    "years": [
      1850,
      1999
    ],
    "folder": "S.F. Hotels-Grand.",
    "library_url": "http://sflib1.sfpl.org:82/record=b1007271~S0",
    "width": 656,
    "height": 400
  },
  "AAB-2260": {
    "title": "Grand Hotel",
    "date": "n.d.",
    "years": [
      1850,
      1999
    ],
    "folder": "S.F. Hotels-Grand.",
    "library_url": "http://sflib1.sfpl.org:82/record=b1007272~S0",
    "width": 504,
    "height": 400
  },
  "AAC-4651": {
    "title": "Wells Fargo Bank on the northeast corner of Market and Montgomery streets",
    "date": "n.d.",
    "years": [
      1850,
      1999
    ],
    "folder": "S.F. Banks-Wells Fargo.",
    "library_url": "http://sflib1.sfpl.org:82/record=b1019521~S0",
    "width": 318,
    "height": 400
  },
  "AAB-4859": {
    "title": "Market St. from Montgomery looking South, showing where New Montgomery St. was cut through. 1863.",
    "date": "1863.",
    "years": [
      1863,
      1863
    ],
    "folder": "S.F. Streets-Market-1860's.",
    "library_url": "http://sflib1.sfpl.org:82/record=b1009824~S0",
    "width": 505,
    "height": 400
  },
  "AAB-7330": {
    "title": "Montgomery street, corner of Market. 1865",
    "date": "1865",
    "years": [
      1865,
      1865
    ],
    "folder": "S.F. Streets-Montgomery-1865.",
    "library_url": "http://sflib1.sfpl.org:82/record=b1012258~S0",
    "width": 412,
    "height": 400
  },
  "AAB-7335": {
    "title": "Montgomery and Market Street, 1865",
    "date": "1865",
    "years": [
      1865,
      1865
    ],
    "folder": "S.F. Streets-Montgomery-1865.",
    "library_url": "http://sflib1.sfpl.org:82/record=b1012262~S0",
    "width": 461,
    "height": 400
  },
  "AAB-4883": {
    "title": "Market Street from Montgomery. 1866.",
    "date": "1866.",
    "years": [
      1866,
      1866
    ],
    "folder": "S.F. Streets-Market-1860's.",
    "library_url": "http://sflib1.sfpl.org:82/record=b1009848~S0",
    "width": 486,
    "height": 400
  },
  "AAB-2253": {
    "title": "Grand Hotel",
    "date": "1869",
    "years": [
      1869,
      1869
    ],
    "folder": "S.F. Hotels-Grand.",
    "library_url": "http://sflib1.sfpl.org:82/record=b1007265~S0",
    "width": 455,
    "height": 400
  },
  "AAB-2255": {
    "title": "Grand Hotel",
    "date": "1869",
    "years": [
      1869,
      1869
    ],
    "folder": "S.F. Hotels-Grand.",
    "library_url": "http://sflib1.sfpl.org:82/record=b1007267~S0",
    "width": 522,
    "height": 400
  },
  "AAB-2254": {
    "title": "Grand Hotel",
    "date": "1870",
    "years": [
      1870,
      1870
    ],
    "folder": "S.F. Hotels-Grand.",
    "library_url": "http://sflib1.sfpl.org:82/record=b1007266~S0",
    "width": 501,
    "height": 400
  },
  "AAB-2256": {
    "title": "Grand Hotel",
    "date": "1870",
    "years": [
      1870,
      1870
    ],
    "folder": "S.F. Hotels-Grand.",
    "library_url": "http://sflib1.sfpl.org:82/record=b1007268~S0",
    "width": 480,
    "height": 400
  },
  "AAB-2250": {
    "title": "Grand Hotel",
    "date": "ca.1874",
    "years": [
      1873,
      1875
    ],
    "folder": "S.F. Hotels-Grand.",
    "library_url": "http://sflib1.sfpl.org:82/record=b1007262~S0",
    "width": 510,
    "height": 400
  },
  "AAB-2251": {
    "title": "Grand Hotel",
    "date": "1874 Apr.",
    "years": [
      1874,
      1874
    ],
    "folder": "S.F. Hotels-Grand.",
    "library_url": "http://sflib1.sfpl.org:82/record=b1007263~S0",
    "width": 491,
    "height": 400
  },
  "AAB-2248": {
    "title": "Grand Hotel",
    "date": "1874",
    "years": [
      1874,
      1874
    ],
    "folder": "S.F. Hotels-Grand.",
    "library_url": "http://sflib1.sfpl.org:82/record=b1007260~S0",
    "width": 482,
    "height": 400
  },
  "AAB-2249": {
    "title": "Grand Hotel",
    "date": "1874",
    "years": [
      1874,
      1874
    ],
    "folder": "S.F. Hotels-Grand.",
    "library_url": "http://sflib1.sfpl.org:82/record=b1007261~S0",
    "width": 520,
    "height": 400
  },
  "AAB-4878": {
    "title": "Market & Montgomery Sts. 1875",
    "date": "1875",
    "years": [
      1875,
      1875
    ],
    "folder": "S.F. Streets-Market-1870's.",
    "library_url": "http://sflib1.sfpl.org:82/record=b1009843~S0",
    "width": 508,
    "height": 400
  },
  "AAB-7282": {
    "title": "Montgomery street from Market. Circa, 1875",
    "date": "1875",
    "years": [
      1875,
      1875
    ],
    "folder": "S.F. Streets-Montgomery-1870's.",
    "library_url": "http://sflib1.sfpl.org:82/record=b1012211~S0",
    "width": 344,
    "height": 400
  },
  "AAB-4760": {
    "title": "New Montgomery from Market Street. Palace Hotel. 1876",
    "date": "1876",
    "years": [
      1876,
      1876
    ],
    "folder": "S.F. Streets-New Montgomery-1870's.",
    "library_url": "http://sflib1.sfpl.org:82/record=b1009732~S0",
    "width": 457,
    "height": 400
  },
  "AAB-4762": {
    "title": "New Montgomery and Annie streets. Showing the Palace Hotel. 1876",
    "date": "1876",
    "years": [
      1876,
      1876
    ],
    "folder": "S.F. Streets-New Montgomery-1870's.",
    "library_url": "http://sflib1.sfpl.org:82/record=b1009734~S0",
    "width": 479,
    "height": 400
  },
  "AAC-8200": {
    "title": "City Railroad Company horse car at Market and Montgomery streets",
    "date": "1879",
    "years": [
      1879,
      1879
    ],
    "folder": "S.F. Transportation-Horse Cars.",
    "library_url": "http://sflib1.sfpl.org:82/record=b1023056~S0",
    "width": 314,
    "height": 400
  },
  "AAB-4763": {
    "title": "New Montgomery. 1880?",
    "date": "1880?",
    "years": [
      1879,
      1881
    ],
    "folder": "S.F. Streets-New Montgomery-1880's.",
    "library_url": "http://sflib1.sfpl.org:82/record=b1009735~S0",
    "width": 402,
    "height": 400
  },
  "AAB-2252": {
    "title": "Grand Hotel, Market Street and New Montgomery",
    "date": "1880",
    "years": [
      1880,
      1880
    ],
    "folder": "S.F. Hotels-Grand.",
    "library_url": "http://sflib1.sfpl.org:82/record=b1007264~S0",
    "width": 584,
    "height": 400
  },
  "AAB-7312": {
    "title": "Montgomery St. from Market, 1880",
    "date": "1880",
    "years": [
      1880,
      1880
    ],
    "folder": "S.F. Streets-Montgomery-1880's.",
    "library_url": "http://sflib1.sfpl.org:82/record=b1012240~S0",
    "width": 253,
    "height": 400
  },
  "AAB-4764": {
    "title": "New Montgomery Street",
    "date": "188-",
    "years": [
      1880,
      1889
    ],
    "folder": "S.F. Streets-New Montgomery-1880's.",
    "library_url": "http://sflib1.sfpl.org:82/record=b1009736~S0",
    "width": 486,
    "height": 400
  },
  "AAB-4900": {
    "title": "Market east of Montgomery",
    "date": "188-?",
    "years": [
      1880,
      1889
    ],
    "folder": "S.F. Streets-Market-1880's.",
    "library_url": "http://sflib1.sfpl.org:82/record=b1009862~S0",
    "width": 337,
    "height": 400
  },
  "AAB-4895": {
    "title": "Crowd of people at Market and Montgomery streets",
    "date": "1883",
    "years": [
      1883,
      1883
    ],
    "folder": "S.F. Streets-Market-1880's.",
    "library_url": "http://sflib1.sfpl.org:82/record=b1009857~S0",
    "width": 586,
    "height": 400
  },
  "AAB-4766": {
    "title": "New Montgomery Street, 1885",
    "date": "1885",
    "years": [
      1885,
      1885
    ],
    "folder": "S.F. Streets-New Montgomery-1880's.",
    "library_url": "http://sflib1.sfpl.org:82/record=b1009738~S0",
    "width": 581,
    "height": 400
  },
  "AAB-7317": {
    "title": "STREET VIEWS OF SAN FRANCISCO - Montgomery Street, from Market, Looking North",
    "date": "ca. 1889",
    "years": [
      1888,
      1890
    ],
    "folder": "S.F. Streets-Montgomery-1880's.",
    "library_url": "http://sflib1.sfpl.org:82/record=b1012245~S0",
    "width": 282,
    "height": 400
  },
  "AAB-7254": {
    "title": "Montgomery Street From Market (Present Day)",
    "date": "1896",
    "years": [
      1896,
      1896
    ],
    "folder": "S.F. Streets-Montgomery-1890's.",
    "library_url": "http://sflib1.sfpl.org:82/record=b1012184~S0",
    "width": 319,
    "height": 400
  },
  "AAB-6254": {
    "title": "Crowd of people watching a parade on Market Street, east of Montgomery",
    "date": "1899",
    "years": [
      1899,
      1899
    ],
    "folder": "S.F. Streets-Market-1890's.",
    "library_url": "http://sflib1.sfpl.org:82/record=b1011195~S0",
    "width": 510,
    "height": 400
  },
  "AAB-7338": {
    "title": "Montgomery street at Market. 1903",
    "date": "1903",
    "years": [
      1903,
      1903
    ],
    "folder": "S.F. Streets-Montgomery-1900's.",
    "library_url": "http://sflib1.sfpl.org:82/record=b1012265~S0",
    "width": 467,
    "height": 400
  },
  "AAB-6173": {
    "title": "Market St. below Montgomery",
    "date": "1905 Oct. 3",
    "years": [
      1905,
      1905
    ],
    "folder": "S.F. Streets-Market-1905.",
    "library_url": "http://sflib1.sfpl.org:82/record=b1011116~S0",
    "width": 527,
    "height": 400
  },
  "AAC-3358": {
    "title": "Looking up Market Street from Sansome on third day of fire, with Palace Hotel and Call Building on left",
    "date": "1906 Apr. 20",
    "years": [
      1906,
      1906
    ],
    "folder": "S.F. Earthquakes-1906-Streets-Market Street.",
    "library_url": "http://sflib1.sfpl.org:82/record=b1018233~S0",
    "width": 303,
    "height": 400
  },
  "AAC-3984": {
    "title": "Palace Hotel on fire",
    "date": "1906 Apr.",
    "years": [
      1906,
      1906
    ],
    "folder": "S.F. Earthquakes-1906-Hotels-Palace Hotel.",
    "library_url": "http://sflib1.sfpl.org:82/record=b1018855~S0",
    "width": 596,
    "height": 400
  },
  "AAC-2600": {
    "title": "The Humboldt Savings Bank, at 626 Market Street, after the 1906 earthquake",
    "date": "1906",
    "years": [
      1906,
      1906
    ],
    "folder": "S.F. Earthquakes-1906-Banks-Humboldt Savings Bank.",
    "library_url": "http://sflib1.sfpl.org:82/record=b1017489~S0",
    "width": 288,
    "height": 400
  },
  "AAC-2601": {
    "title": "The Humboldt Savings Bank, at 626 Market Street, after the 1906 earthquake",
    "date": "1906",
    "years": [
      1906,
      1906
    ],
    "folder": "S.F. Earthquakes-1906-Banks-Humboldt Savings Bank.",
    "library_url": "http://sflib1.sfpl.org:82/record=b1017490~S0",
    "width": 303,
    "height": 400
  },
  "AAC-3351": {
    "title": "Looking west on Market Street from near Montgomery",
    "date": "1906",
    "years": [
      1906,
      1906
    ],
    "folder": "S.F. Earthquakes-1906-Streets-Market Street.",
    "library_url": "http://sflib1.sfpl.org:82/record=b1018226~S0",
    "width": 502,
    "height": 400
  },
  "AAC-3368": {
    "title": "Montgomery street looking north from Market, the Mills and Hayward Buildings in distance",
    "date": "1906",
    "years": [
      1906,
      1906
    ],
    "folder": "S.F. Earthquakes-1906-Streets-Montgomery Street.",
    "library_url": "http://sflib1.sfpl.org:82/record=b1018243~S0",
    "width": 749,
    "height": 400
  },
  "AAC-3369": {
    "title": "Looking along Montgomery St. from Market, April, 1906",
    "date": "1906",
    "years": [
      1906,
      1906
    ],
    "folder": "S.F. Earthquakes-1906-Streets-Montgomery Street.",
    "library_url": "http://sflib1.sfpl.org:82/record=b1018244~S0",
    "width": 544,
    "height": 400
  },
  "AAC-3888": {
    "title": "Dynamiting Masonic Hall, Montgomery and Market streets",
    "date": "1906",
    "years": [
      1906,
      1906
    ],
    "folder": "S.F. Earthquakes-1906-Districts-Downtown.",
    "library_url": "http://sflib1.sfpl.org:82/record=b1018760~S0",
    "width": 311,
    "height": 400
  },
  "AAC-3981": {
    "title": "Last of the old Palace Hotel, - the Market St. Portal",
    "date": "1906",
    "years": [
      1906,
      1906
    ],
    "folder": "S.F. Earthquakes-1906-Hotels-Palace Hotel.",
    "library_url": "http://sflib1.sfpl.org:82/record=b1018852~S0",
    "width": 322,
    "height": 400
  },
  "AAC-3982": {
    "title": "Ruins of the Grand Hotel and the Palace Hotel, with Call Building in the background",
    "date": "1906",
    "years": [
      1906,
      1906
    ],
    "folder": "S.F. Earthquakes-1906-Hotels-Palace Hotel.",
    "library_url": "http://sflib1.sfpl.org:82/record=b1018853~S0",
    "width": 521,
    "height": 400
  },
  "AAC-3983": {
    "title": "Palace Hotel",
    "date": "1906",
    "years": [
      1906,
      1906
    ],
    "folder": "S.F. Earthquakes-1906-Hotels-Palace Hotel.",
    "library_url": "http://sflib1.sfpl.org:82/record=b1018854~S0",
    "width": 526,
    "height": 400
  },
  "AAC-3985": {
    "title": "Ruins of the Palace Hotel at Market and New Montgomery streets",
    "date": "1906",
    "years": [
      1906,
      1906
    ],
    "folder": "S.F. Earthquakes-1906-Hotels-Palace Hotel.",
    "library_url": "http://sflib1.sfpl.org:82/record=b1018856~S0",
    "width": 537,
    "height": 400
  },
  "AAC-3986": {
    "title": "Palace Hotel",
    "date": "1906",
    "years": [
      1906,
      1906
    ],
    "folder": "S.F. Earthquakes-1906-Hotels-Palace Hotel.",
    "library_url": "http://sflib1.sfpl.org:82/record=b1018857~S0",
    "width": 236,
    "height": 400
  },
  "AAC-3988": {
    "title": "The Palace Hotel&#59; Grand Hotel to the left",
    "date": "1906",
    "years": [
      1906,
      1906
    ],
    "folder": "S.F. Earthquakes-1906-Hotels-Palace Hotel.",
    "library_url": "http://sflib1.sfpl.org:82/record=b1018859~S0",
    "width": 626,
    "height": 400
  },
  "AAC-3989": {
    "title": "Palace Hotel",
    "date": "1906",
    "years": [
      1906,
      1906
    ],
    "folder": "S.F. Earthquakes-1906-Hotels-Palace Hotel.",
    "library_url": "http://sflib1.sfpl.org:82/record=b1018860~S0",
    "width": 565,
    "height": 400
  },
  "AAC-3990": {
    "title": "Palace Hotel",
    "date": "1906",
    "years": [
      1906,
      1906
    ],
    "folder": "S.F. Earthquakes-1906-Hotels-Palace Hotel.",
    "library_url": "http://sflib1.sfpl.org:82/record=b1018861~S0",
    "width": 561,
    "height": 400
  },
  "AAC-3991": {
    "title": "Ruins of the Palace Hotel at Market and New Montgomery streets, with Lotta's Fountain in right foreground",
    "date": "1906",
    "years": [
      1906,
      1906
    ],
    "folder": "S.F. Earthquakes-1906-Hotels-Palace Hotel.",
    "library_url": "http://sflib1.sfpl.org:82/record=b1018862~S0",
    "width": 678,
    "height": 400
  },
  "AAC-3992": {
    "title": "Ruins of the Palace Hotel at Market and New Montgomery streets",
    "date": "1906",
    "years": [
      1906,
      1906
    ],
    "folder": "S.F. Earthquakes-1906-Hotels-Palace Hotel.",
    "library_url": "http://sflib1.sfpl.org:82/record=b1018863~S0",
    "width": 522,
    "height": 400
  },
  "AAC-3993": {
    "title": "Ruins of the Palace Hotel at Market and New Montgomery streets",
    "date": "1906",
    "years": [
      1906,
      1906
    ],
    "folder": "S.F. Earthquakes-1906-Hotels-Palace Hotel.",
    "library_url": "http://sflib1.sfpl.org:82/record=b1018864~S0",
    "width": 559,
    "height": 400
  },
  "AAC-3994": {
    "title": "Palace Hotel",
    "date": "1906",
    "years": [
      1906,
      1906
    ],
    "folder": "S.F. Earthquakes-1906-Hotels-Palace Hotel.",
    "library_url": "http://sflib1.sfpl.org:82/record=b1018865~S0",
    "width": 535,
    "height": 400
  },
  "AAC-3995": {
    "title": "Ruins of the Palace Hotel at Market and New Montgomery streets, with Lotta's Fountain in right foreground",
    "date": "1906",
    "years": [
      1906,
      1906
    ],
    "folder": "S.F. Earthquakes-1906-Hotels-Palace Hotel.",
    "library_url": "http://sflib1.sfpl.org:82/record=b1018866~S0",
    "width": 566,
    "height": 400
  },
  "AAC-3996": {
    "title": "Ruins of the Palace Hotel at Market and New Montgomery streets",
    "date": "1906",
    "years": [
      1906,
      1906
    ],
    "folder": "S.F. Earthquakes-1906-Hotels-Palace Hotel.",
    "library_url": "http://sflib1.sfpl.org:82/record=b1018867~S0",
    "width": 568,
    "height": 400
  },
  "AAC-3997": {
    "title": "Ruins of the Grand Hotel and the Palace Hotel, with Call Building in the background",
    "date": "1906",
    "years": [
      1906,
      1906
    ],
    "folder": "S.F. Earthquakes-1906-Hotels-Palace Hotel.",
    "library_url": "http://sflib1.sfpl.org:82/record=b1018868~S0",
    "width": 566,
    "height": 400
  },
  "AAC-3998": {
    "title": "Ruins of  the Palace Hotel",
    "date": "1906",
    "years": [
      1906,
      1906
    ],
    "folder": "S.F. Earthquakes-1906-Hotels-Palace Hotel.",
    "library_url": "http://sflib1.sfpl.org:82/record=b1018869~S0",
    "width": 501,
    "height": 400
  },
  "AAC-3999": {
    "title": "Ruins of  the Palace Hotel",
    "date": "1906",
    "years": [
      1906,
      1906
    ],
    "folder": "S.F. Earthquakes-1906-Hotels-Palace Hotel.",
    "library_url": "http://sflib1.sfpl.org:82/record=b1018870~S0",
    "width": 498,
    "height": 400
  },
  "AAC-4000": {
    "title": "Ruins of  the Palace Hotel",
    "date": "1906",
    "years": [
      1906,
      1906
    ],
    "folder": "S.F. Earthquakes-1906-Hotels-Palace Hotel.",
    "library_url": "http://sflib1.sfpl.org:82/record=b1018871~S0",
    "width": 522,
    "height": 400
  },
  "AAC-4001": {
    "title": "Palace Hotel, rear view",
    "date": "1906",
    "years": [
      1906,
      1906
    ],
    "folder": "S.F. Earthquakes-1906-Hotels-Palace Hotel.",
    "library_url": "http://sflib1.sfpl.org:82/record=b1018872~S0",
    "width": 569,
    "height": 400
  },
  "AAC-4002": {
    "title": "Palace Hotel",
    "date": "1906",
    "years": [
      1906,
      1906
    ],
    "folder": "S.F. Earthquakes-1906-Hotels-Palace Hotel.",
    "library_url": "http://sflib1.sfpl.org:82/record=b1018873~S0",
    "width": 305,
    "height": 400
  },
  "AAC-4003": {
    "title": "The Mirror No. 2, The Great San Francisco Fire",
    "date": "1906",
    "years": [
      1906,
      1906
    ],
    "folder": "S.F. Earthquakes-1906-Hotels-Palace Hotel.",
    "library_url": "http://sflib1.sfpl.org:82/record=b1018874~S0",
    "width": 506,
    "height": 400
  },
  "AAC-5072": {
    "title": "San Francisco in ruins after the 1906 earthquake and fire, view north from Market and Montgomery street",
    "date": "1906",
    "years": [
      1906,
      1906
    ],
    "folder": "S.F. Earthquakes-1906-General Views.",
    "library_url": "http://sflib1.sfpl.org:82/record=b1019941~S0",
    "width": 567,
    "height": 400
  },
  "AAB-7285": {
    "title": "Montgomery and Market Street",
    "date": "1910",
    "years": [
      1910,
      1910
    ],
    "folder": "S.F. Streets-Montgomery-1910's.",
    "library_url": "http://sflib1.sfpl.org:82/record=b1012214~S0",
    "width": 527,
    "height": 400
  },
  "AAB-7286": {
    "title": "Montgomery Street near Market",
    "date": "191-",
    "years": [
      1910,
      1919
    ],
    "folder": "S.F. Streets-Montgomery-1910's.",
    "library_url": "http://sflib1.sfpl.org:82/record=b1012215~S0",
    "width": 305,
    "height": 400
  },
  "AAB-6311": {
    "title": "Market Street, looking east from Montgomery Street",
    "date": "1934",
    "years": [
      1934,
      1934
    ],
    "folder": "S.F. Streets-Market-1934.",
    "library_url": "http://sflib1.sfpl.org:82/record=b1011252~S0",
    "width": 539,
    "height": 400
  },
  "AAB-6324": {
    "title": "Cave-in at Market and Montgomery streets",
    "date": "1935 Feb. 4",
    "years": [
      1935,
      1935
    ],
    "folder": "S.F. Streets-Market-1935.",
    "library_url": "http://sflib1.sfpl.org:82/record=b1011265~S0",
    "width": 470,
    "height": 400
  },
  "AAB-6325": {
    "title": "Workers repairing cave-in at Market and Montgomery streets",
    "date": "1935 Feb. 4",
    "years": [
      1935,
      1935
    ],
    "folder": "S.F. Streets-Market-1935.",
    "library_url": "http://sflib1.sfpl.org:82/record=b1011266~S0",
    "width": 591,
    "height": 400
  },
  "AAB-6326": {
    "title": "Workers repairing cave-in at Market and Montgomery streets",
    "date": "1935 Feb. 7",
    "years": [
      1935,
      1935
    ],
    "folder": "S.F. Streets-Market-1935.",
    "library_url": "http://sflib1.sfpl.org:82/record=b1011267~S0",
    "width": 496,
    "height": 400
  },
  "AAB-2316": {
    "title": "Palace Hotel, Market and New Montgomery streets",
    "date": "1938 Feb. 3",
    "years": [
      1938,
      1938
    ],
    "folder": "S.F. Hotels-Palace-Exteriors-(After 1906).",
    "library_url": "http://sflib1.sfpl.org:82/record=b1007328~S0",
    "width": 144,
    "height": 400
  },
  "AAC-5411": {
    "title": "Traders watching the quotation board at the brokerage house of McDonnell & Co., 633 Market Street ",
    "date": "1938 June 30",
    "years": [
      1938,
      1938
    ],
    "folder": "S.F. Stock Exchange-Interiors.",
    "library_url": "http://sflib1.sfpl.org:82/record=b1020278~S0",
    "width": 508,
    "height": 400
  },
  "AAB-7346": {
    "title": "Intersection of Montgomery and Market Street",
    "date": "194-",
    "years": [
      1940,
      1949
    ],
    "folder": "S.F. Streets-Montgomery-1940's.",
    "library_url": "http://sflib1.sfpl.org:82/record=b1012273~S0",
    "width": 318,
    "height": 400
  },
  "AAB-6425": {
    "title": "Automobiles parked diagonally down the center of Market Street, near Montgomery",
    "date": "1946 July 2",
    "years": [
      1946,
      1946
    ],
    "folder": "S.F. Streets-Market-1946.",
    "library_url": "http://sflib1.sfpl.org:82/record=b1011364~S0",
    "width": 530,
    "height": 400
  },
  "AAC-4650": {
    "title": "Wells Fargo Bank at Market and Montgomery streets",
    "date": "1964?",
    "years": [
      1963,
      1965
    ],
    "folder": "S.F. Banks-Wells Fargo.",
    "library_url": "http://sflib1.sfpl.org:82/record=b1019520~S0",
    "width": 317,
    "height": 400
  },
  "AAC-4326": {
    "title": "Bank of America branch at Market and New Montgomery streets",
    "date": "1964 Aug. 10",
    "years": [
      1964,
      1964
    ],
    "folder": "S.F. Banks-Bank of America-Branches-Market/New Montgomery.",
    "library_url": "http://sflib1.sfpl.org:82/record=b1019196~S0",
    "width": 324,
    "height": 400
  },
  "AAC-4632": {
    "title": "People sitting on a wall around a Wells Fargo Bank building near Market and Montgomery streets",
    "date": "1973 Oct.",
    "years": [
      1973,
      1973
    ],
    "folder": "S.F. Banks-Wells Fargo.",
    "library_url": "http://sflib1.sfpl.org:82/record=b1019502~S0",
    "width": 305,
    "height": 400
  },
  "AAC-4633": {
    "title": "People sitting on a wall around a Wells Fargo Bank building near Market and Montgomery streets",
    "date": "1973 Oct.",
    "years": [
      1973,
      1973
    ],
    "folder": "S.F. Banks-Wells Fargo.",
    "library_url": "http://sflib1.sfpl.org:82/record=b1019503~S0",
    "width": 307,
    "height": 400
  },
  "AAC-4634": {
    "title": "Wells Fargo Bank building near Market and Montgomery streets",
    "date": "1973 Oct.",
    "years": [
      1973,
      1973
    ],
    "folder": "S.F. Banks-Wells Fargo.",
    "library_url": "http://sflib1.sfpl.org:82/record=b1019504~S0",
    "width": 501,
    "height": 400
  }
}