{
  "AAB-9304": {
    "title": "Housing on North East corner, Lombard and Lyon Streets, purchased by Pan Pacific International Exposition ",
    "date": "n.d.",
    "years": [
      1850,
      1999
    ],
    "folder": "S.F. Districts-Marina-Housing and Businesses-P.P.I.E.",
    "library_url": "http://sflib1.sfpl.org:82/record=b1014219~S0",
    "width": 500,
    "height": 400
  },
  "AAB-4405": {
    "title": "Lyon St. Northerly From Lombard St.",
    "date": "1933 Jan. 11",
    "years": [
      1933,
      1933
    ],
    "folder": "S.F. Streets-Lyon.",
    "library_url": "http://sflib1.sfpl.org:82/record=b1009383~S0",
    "width": 501,
    "height": 400
  }
}