{
  "AAC-5918": {
    "title": "632 Mansell Street",
    "date": "1926",
    "years": [
      1926,
      1926
    ],
    "folder": "S.F. Residences-632 Mansell St.",
    "library_url": "http://sflib1.sfpl.org:82/record=b1020784~S0",
    "width": 287,
    "height": 400
  },
  "AAC-5919": {
    "title": "632 Mansell Street",
    "date": "1926",
    "years": [
      1926,
      1926
    ],
    "folder": "S.F. Residences-632 Mansell St.",
    "library_url": "http://sflib1.sfpl.org:82/record=b1020785~S0",
    "width": 551,
    "height": 400
  }
}