{
  "aad-8133": {
    "title": "Old Engine 1 Fire House, 449 Pacific Avenue",
    "date": "1895",
    "years": [
      1895,
      1895
    ],
    "folder": "S.F. Fire Department-Engine 1 (Old).",
    "library_url": "http://sflib1.sfpl.org:82/record=b1034013~S0",
    "width": 310,
    "height": 400
  },
  "aad-8132": {
    "title": "Old Engine 1 Fire House, 449 Pacific Avenue",
    "date": "1964 Aug. 16",
    "years": [
      1964,
      1964
    ],
    "folder": "S.F. Fire Department-Engine 1 (Old).",
    "library_url": "http://sflib1.sfpl.org:82/record=b1034012~S0",
    "width": 323,
    "height": 400
  }
}