{
  "AAB-3892": {
    "title": "View of Grant Avenue in Chinatown from Vallejo Street",
    "date": "1972 May 25",
    "years": [
      1972,
      1972
    ],
    "folder": "S.F. Streets-Grant Ave.-1970's.",
    "library_url": "http://sflib1.sfpl.org:82/record=b1008879~S0",
    "width": 279,
    "height": 400
  },
  "AAB-9598": {
    "title": "Grant Avenue and Vallejo street, North Beach",
    "date": "1973 May",
    "years": [
      1973,
      1973
    ],
    "folder": "S.F. Districts-North Beach.",
    "library_url": "http://sflib1.sfpl.org:82/record=b1014510~S0",
    "width": 498,
    "height": 400
  },
  "AAB-2616": {
    "title": "Owners singing in Caffe Trieste",
    "date": "1974 Mar.",
    "years": [
      1974,
      1974
    ],
    "folder": "S.F. Restaurants-Caffe Trieste.",
    "library_url": "http://sflib1.sfpl.org:82/record=b1007628~S0",
    "width": 502,
    "height": 400
  },
  "AAB-2629": {
    "title": "Caffe Trieste, owner's son Johnny singing opera",
    "date": "1974 Mar.",
    "years": [
      1974,
      1974
    ],
    "folder": "S.F. Restaurants-Caffe Trieste.",
    "library_url": "http://sflib1.sfpl.org:82/record=b1007641~S0",
    "width": 316,
    "height": 400
  },
  "AAB-2633": {
    "title": "Caffe Trieste, North Beach",
    "date": "1974 Mar",
    "years": [
      1974,
      1974
    ],
    "folder": "S.F. Restaurants-Caffe Trieste.",
    "library_url": "http://sflib1.sfpl.org:82/record=b1007645~S0",
    "width": 580,
    "height": 400
  },
  "AAB-2618": {
    "title": "Caffe Trieste, Grant & Vallejo in North Beach",
    "date": "1974 June",
    "years": [
      1974,
      1974
    ],
    "folder": "S.F. Restaurants-Caffe Trieste.",
    "library_url": "http://sflib1.sfpl.org:82/record=b1007630~S0",
    "width": 591,
    "height": 400
  },
  "AAB-2630": {
    "title": "Caffe Trieste, North Beach",
    "date": "1977 Apr.",
    "years": [
      1977,
      1977
    ],
    "folder": "S.F. Restaurants-Caffe Trieste.",
    "library_url": "http://sflib1.sfpl.org:82/record=b1007642~S0",
    "width": 593,
    "height": 400
  },
  "AAB-2628": {
    "title": "Caffe Trieste, Grant & Vallejo in North Beach",
    "date": "1977 May",
    "years": [
      1977,
      1977
    ],
    "folder": "S.F. Restaurants-Caffe Trieste.",
    "library_url": "http://sflib1.sfpl.org:82/record=b1007640~S0",
    "width": 606,
    "height": 400
  },
  "AAB-2631": {
    "title": "Caffe Trieste, North Beach",
    "date": "1977 May",
    "years": [
      1977,
      1977
    ],
    "folder": "S.F. Restaurants-Caffe Trieste.",
    "library_url": "http://sflib1.sfpl.org:82/record=b1007643~S0",
    "width": 594,
    "height": 400
  },
  "AAB-2632": {
    "title": "Caffe Trieste, North Beach",
    "date": "1977 May",
    "years": [
      1977,
      1977
    ],
    "folder": "S.F. Restaurants-Caffe Trieste.",
    "library_url": "http://sflib1.sfpl.org:82/record=b1007644~S0",
    "width": 594,
    "height": 400
  },
  "AAB-2635": {
    "title": "Charlie Wildberger, City gardener, sitting in Caffe Trieste, North Beach",
    "date": "1977 May",
    "years": [
      1977,
      1977
    ],
    "folder": "S.F. Restaurants-Caffe Trieste.",
    "library_url": "http://sflib1.sfpl.org:82/record=b1007647~S0",
    "width": 593,
    "height": 400
  }
}