{
  "AAB-0271": {
    "title": "Unidentified students with sculptures at Galileo High School",
    "date": "n.d.",
    "years": [
      1850,
      1999
    ],
    "folder": "S.F. Schools-Secondary-Galileo.",
    "library_url": "http://sflib1.sfpl.org:82/record=b1005326~S0",
    "width": 550,
    "height": 400
  },
  "AAB-0285": {
    "title": "Galileo High School gymnasium building",
    "date": "1923 Nov. 10",
    "years": [
      1923,
      1923
    ],
    "folder": "S.F. Schools-Secondary-Galileo.",
    "library_url": "http://sflib1.sfpl.org:82/record=b1005340~S0",
    "width": 766,
    "height": 400
  },
  "AAB-0291": {
    "title": "Galileo High School",
    "date": "1923 Nov. 10",
    "years": [
      1923,
      1923
    ],
    "folder": "S.F. Schools-Secondary-Galileo.",
    "library_url": "http://sflib1.sfpl.org:82/record=b1005346~S0",
    "width": 953,
    "height": 400
  },
  "AAB-0289": {
    "title": "Bea Haslacher, Paul Denke and Bob Haslacher on the steps of the Galileo High School observatory",
    "date": "1928?",
    "years": [
      1927,
      1929
    ],
    "folder": "S.F. Schools-Secondary-Galileo.",
    "library_url": "http://sflib1.sfpl.org:82/record=b1005344~S0",
    "width": 516,
    "height": 400
  },
  "AAB-0273": {
    "title": "Marching band at Galileo High School ",
    "date": "1929 June 13",
    "years": [
      1929,
      1929
    ],
    "folder": "S.F. Schools-Secondary-Galileo.",
    "library_url": "http://sflib1.sfpl.org:82/record=b1005328~S0",
    "width": 772,
    "height": 400
  },
  "AAB-0269": {
    "title": "Galileo High School",
    "date": "1930 Sept. 4",
    "years": [
      1930,
      1930
    ],
    "folder": "S.F. Schools-Secondary-Galileo.",
    "library_url": "http://sflib1.sfpl.org:82/record=b1005324~S0",
    "width": 601,
    "height": 400
  },
  "AAB-0268": {
    "title": "Group of people posing on the stairs of the observatory on the roof of Galileo School",
    "date": "1933 Jan. 16",
    "years": [
      1933,
      1933
    ],
    "folder": "S.F. Schools-Secondary-Galileo.",
    "library_url": "http://sflib1.sfpl.org:82/record=b1005323~S0",
    "width": 296,
    "height": 400
  },
  "AAB-0288": {
    "title": "R.O.T.C. Officers raising a flag at Galileo High School",
    "date": "1935 Sept. 17",
    "years": [
      1935,
      1935
    ],
    "folder": "S.F. Schools-Secondary-Galileo.",
    "library_url": "http://sflib1.sfpl.org:82/record=b1005343~S0",
    "width": 489,
    "height": 400
  },
  "AAB-0287": {
    "title": "Galileo High School rifle team",
    "date": "1935 Nov. 15",
    "years": [
      1935,
      1935
    ],
    "folder": "S.F. Schools-Secondary-Galileo.",
    "library_url": "http://sflib1.sfpl.org:82/record=b1005342~S0",
    "width": 548,
    "height": 400
  },
  "AAB-0286": {
    "title": "R.O.T.C. at Galileo High School",
    "date": "1935 Nov. 20",
    "years": [
      1935,
      1935
    ],
    "folder": "S.F. Schools-Secondary-Galileo.",
    "library_url": "http://sflib1.sfpl.org:82/record=b1005341~S0",
    "width": 422,
    "height": 400
  },
  "AAB-0270": {
    "title": "Tunnel being Excavated underneath Bay Street for use by Galileo High School students",
    "date": "1937 Mar. 22",
    "years": [
      1937,
      1937
    ],
    "folder": "S.F. Schools-Secondary-Galileo.",
    "library_url": "http://sflib1.sfpl.org:82/record=b1005325~S0",
    "width": 280,
    "height": 400
  },
  "AAB-0274": {
    "title": "Unidentified man standing on the steps of the Galileo High School observatory",
    "date": "1939 May 7",
    "years": [
      1939,
      1939
    ],
    "folder": "S.F. Schools-Secondary-Galileo.",
    "library_url": "http://sflib1.sfpl.org:82/record=b1005329~S0",
    "width": 356,
    "height": 400
  },
  "AAB-0267": {
    "title": "William A. Weiland, Edith Pence and William J. Drew at a meeting of school principals",
    "date": "1943 May 13",
    "years": [
      1943,
      1943
    ],
    "folder": "S.F. Schools-Secondary-Galileo.",
    "library_url": "http://sflib1.sfpl.org:82/record=b1005322~S0",
    "width": 498,
    "height": 400
  },
  "AAB-0277": {
    "title": "One section of an enlarger room in the Galileo High School photography laboratory",
    "date": "1948 Sept. 8",
    "years": [
      1948,
      1948
    ],
    "folder": "S.F. Schools-Secondary-Galileo.",
    "library_url": "http://sflib1.sfpl.org:82/record=b1005332~S0",
    "width": 321,
    "height": 400
  },
  "AAB-0278": {
    "title": "Chemical mixing room in the Galileo High School photography laboratory",
    "date": "1948 Sept. 8",
    "years": [
      1948,
      1948
    ],
    "folder": "S.F. Schools-Secondary-Galileo.",
    "library_url": "http://sflib1.sfpl.org:82/record=b1005333~S0",
    "width": 498,
    "height": 400
  },
  "AAB-0279": {
    "title": "Adult students working in the enlarging and developing section of the Galileo High School photography laboratory",
    "date": "1948 Sept. 8",
    "years": [
      1948,
      1948
    ],
    "folder": "S.F. Schools-Secondary-Galileo.",
    "library_url": "http://sflib1.sfpl.org:82/record=b1005334~S0",
    "width": 498,
    "height": 400
  },
  "AAB-0280": {
    "title": "Photography class &#34;shooting room&#34; at Galileo High School",
    "date": "1948 Sept. 8",
    "years": [
      1948,
      1948
    ],
    "folder": "S.F. Schools-Secondary-Galileo.",
    "library_url": "http://sflib1.sfpl.org:82/record=b1005335~S0",
    "width": 500,
    "height": 400
  },
  "AAB-0281": {
    "title": "Adult photography class at Galileo High School",
    "date": "1948 Sept. 8",
    "years": [
      1948,
      1948
    ],
    "folder": "S.F. Schools-Secondary-Galileo.",
    "library_url": "http://sflib1.sfpl.org:82/record=b1005336~S0",
    "width": 498,
    "height": 400
  },
  "AAB-0275": {
    "title": "Photography class at Galileo High School",
    "date": "1948 Oct. 1",
    "years": [
      1948,
      1948
    ],
    "folder": "S.F. Schools-Secondary-Galileo.",
    "library_url": "http://sflib1.sfpl.org:82/record=b1005330~S0",
    "width": 503,
    "height": 400
  },
  "AAB-0276": {
    "title": "Adult photography class at Galileo High School",
    "date": "1948 Oct. 1",
    "years": [
      1948,
      1948
    ],
    "folder": "S.F. Schools-Secondary-Galileo.",
    "library_url": "http://sflib1.sfpl.org:82/record=b1005331~S0",
    "width": 498,
    "height": 400
  },
  "AAB-0283": {
    "title": "Adult photography class at Galileo High School",
    "date": "1948 Oct. 1",
    "years": [
      1948,
      1948
    ],
    "folder": "S.F. Schools-Secondary-Galileo.",
    "library_url": "http://sflib1.sfpl.org:82/record=b1005338~S0",
    "width": 502,
    "height": 400
  },
  "AAB-0284": {
    "title": "Adult photography class at Galileo High School",
    "date": "1948 Oct. 1",
    "years": [
      1948,
      1948
    ],
    "folder": "S.F. Schools-Secondary-Galileo.",
    "library_url": "http://sflib1.sfpl.org:82/record=b1005339~S0",
    "width": 495,
    "height": 400
  },
  "AAB-0282": {
    "title": "Photo lab classroom at Galileo High School",
    "date": "1955 Sept. 13",
    "years": [
      1955,
      1955
    ],
    "folder": "S.F. Schools-Secondary-Galileo.",
    "library_url": "http://sflib1.sfpl.org:82/record=b1005337~S0",
    "width": 503,
    "height": 400
  },
  "AAB-0292": {
    "title": "Galileo High School photo lab",
    "date": "1955",
    "years": [
      1955,
      1955
    ],
    "folder": "S.F. Schools-Secondary-Galileo.",
    "library_url": "http://sflib1.sfpl.org:82/record=b1005347~S0",
    "width": 500,
    "height": 400
  },
  "AAB-0293": {
    "title": "Students on the campus of Galileo High School",
    "date": "1958 Oct. 16",
    "years": [
      1958,
      1958
    ],
    "folder": "S.F. Schools-Secondary-Galileo.",
    "library_url": "http://sflib1.sfpl.org:82/record=b1005348~S0",
    "width": 361,
    "height": 400
  },
  "AAB-0272": {
    "title": "George Miller inspecting loaves of bread as they come out of the oven in the kitchen at Galileo High School ",
    "date": "1962 Apr. 13",
    "years": [
      1962,
      1962
    ],
    "folder": "S.F. Schools-Secondary-Galileo.",
    "library_url": "http://sflib1.sfpl.org:82/record=b1005327~S0",
    "width": 320,
    "height": 400
  },
  "AAB-0290": {
    "title": "Galileo High School, 1055 Bay Street",
    "date": "1964 June 18",
    "years": [
      1964,
      1964
    ],
    "folder": "S.F. Schools-Secondary-Galileo.",
    "library_url": "http://sflib1.sfpl.org:82/record=b1005345~S0",
    "width": 494,
    "height": 400
  }
}